<?xml version="1.0" encoding="UTF-8" standalone="no"?><aiki.fight.items.Boost>
<r class="aiki.fight.items.Boost" field="winPp" value="3"/>
<sm class="aiki.fight.items.Boost" field="happiness">
<java.lang.String class="m" key="" value="FAIBLO_BALL"/>
<java.lang.String class="m" key="" value="SCUBA_BALL"/>
<java.lang.String class="m" key="" value="HONOR_BALL"/>
<java.lang.String class="m" key="" value="BIS_BALL"/>
<java.lang.String class="m" key="" value="LUNE_BALL"/>
<java.lang.String class="m" key="" value="SPEED_BALL"/>
<java.lang.String class="m" key="" value="LUXE_BALL"/>
<java.lang.String class="m" key="" value="SOIN_BALL"/>
<java.lang.String class="m" key="" value="MASTER_BALL"/>
<java.lang.String class="m" key="" value="CHRONO_BALL"/>
<java.lang.String class="m" key="" value="POKE_BALL"/>
<java.lang.String class="m" key="" value="SUPER_BALL"/>
<java.lang.String class="m" key="" value="RAPIDE_BALL"/>
<java.lang.String class="m" key="" value="NIVEAU_BALL"/>
<java.lang.String class="m" key="" value="SOMBRE_BALL"/>
<java.lang.String class="m" key="" value="HYPER_BALL"/>
<java.lang.String class="m" key="" value="MASSE_BALL"/>
<java.lang.String class="m" key="" value="LOVE_BALL"/>
<java.lang.String class="m" key="" value="COMPET_BALL"/>
<java.lang.String class="m" key="" value="APPAT_BALL"/>
<java.lang.String class="m" key="" value="COPAIN_BALL"/>
<java.lang.String class="m" key="" value="FILET_BALL"/>
<java.lang.Short class="m" value="2"/>
<java.lang.Short class="m" value="2"/>
<java.lang.Short class="m" value="2"/>
<java.lang.Short class="m" value="2"/>
<java.lang.Short class="m" value="2"/>
<java.lang.Short class="m" value="2"/>
<java.lang.Short class="m" value="6"/>
<java.lang.Short class="m" value="2"/>
<java.lang.Short class="m" value="2"/>
<java.lang.Short class="m" value="2"/>
<java.lang.Short class="m" value="2"/>
<java.lang.Short class="m" value="2"/>
<java.lang.Short class="m" value="2"/>
<java.lang.Short class="m" value="2"/>
<java.lang.Short class="m" value="2"/>
<java.lang.Short class="m" value="2"/>
<java.lang.Short class="m" value="2"/>
<java.lang.Short class="m" value="2"/>
<java.lang.Short class="m" value="2"/>
<java.lang.Short class="m" value="2"/>
<java.lang.Short class="m" value="2"/>
<java.lang.Short class="m" value="2"/>
</sm>
<em class="aiki.fight.items.Boost" field="evs"/>
<java.lang.Integer class="aiki.fight.items.Item" field="price" value="9800"/>
</aiki.fight.items.Boost>